{
  "case_id": "CRV4-132",
  "data_role": "calibration",
  "fixture_id": "crv4-calibration-workload-mix-132",
  "fixture_set_id": "synthetic-calibration-redesign-v4",
  "fixture_set_version": "1.0.0",
  "outcomes": [
    {
      "block_position_index": 1,
      "candidate_token_id": 6321,
      "decode_round": 0,
      "observed_acceptance": false,
      "prefix_survival_label": false,
      "trace_id": "crv4-calibration-workload-trace-132"
    },
    {
      "block_position_index": 2,
      "candidate_token_id": 6322,
      "decode_round": 0,
      "observed_acceptance": true,
      "prefix_survival_label": false,
      "trace_id": "crv4-calibration-workload-trace-132"
    },
    {
      "block_position_index": 3,
      "candidate_token_id": 6323,
      "decode_round": 0,
      "observed_acceptance": true,
      "prefix_survival_label": false,
      "trace_id": "crv4-calibration-workload-trace-132"
    },
    {
      "block_position_index": 4,
      "candidate_token_id": 6324,
      "decode_round": 0,
      "observed_acceptance": true,
      "prefix_survival_label": false,
      "trace_id": "crv4-calibration-workload-trace-132"
    }
  ],
  "scenario_family_id": "CRV4-CAL-WORKLOAD-MIX",
  "schema_version": "calibration-redesign-v4-case-v1",
  "source_type": "synthetic",
  "split": "calibration",
  "trace_id": "crv4-calibration-workload-trace-132"
}
